<RothC xmlns="http://tag2e.googlecode.com/files/RothC" xmlns:xsi="http://www.w3.org/2001/XMLSchema-instance" xsi:schemaLocation="http://tag2e.googlecode.com/files/RothC http://tag2e.googlecode.com/files/RothC.xsd">
  <a>
    <a1 const="1" max="1.9323" min="1.9323">
      1.9323
    </a1>
    <a2 const="1" max="31.1274" min="31.1274">
      31.127352
    </a2>
    <a3 const="1" max="18.3" min="18.3">
      18.3
    </a3>
    
  </a>
  <b>
    <b1 const="1" max="0.220054" min="0.220054">
      0.220054
    </b1>
    <b2 const="1" max="1" min="1">
      1
    </b2>
    <b3 const="1" max="0" min="0">
      0.0
    </b3>
    
  </b>
  <c>
    <c1 const="1" max="0.6" min="0.6">
      0.6
    </c1>
    <c2 const="1" max="1" min="1">
      1
    </c2>
    
  </c>
  <k>
    <DPM const="1" max="10.2" min="10.2">
      10.2
    </DPM>
    <RPM const="1" max="0.3" min="0.3">
      0.3
    </RPM>
    <BIO const="1" max="0.66" min="0.66">
      0.66
    </BIO>
    <HUM const="1" max="0.02" min="0.02">
      0.02
    </HUM>
    
  </k>
  <x>
    <x1 const="1" max="0.46" min="0.46">
      0.46
    </x1>
    <x2 const="1" max="1.85" min="1.85">
      1.85
    </x2>
    <x3 const="1" max="107.897" min="107.897">
      107.897173
    </x3>
    <x4 const="1" max="-0.0786" min="-0.0786">
      -0.0786
    </x4>
    
  </x>
  <PlantFractions>
    <PlantFraction id="0" name="default">
      <description>
        The default ratio parameter for agricultural crops and grassland
      </description>
      <DPM const="1" max="0.59" min="0.59">
        0.59
      </DPM>
      <RPM const="1" max="0.41" min="0.41">
        0.41
      </RPM>
      <HUM const="1" max="0" min="0">
        0
      </HUM>
      
    </PlantFraction>
    <PlantFraction id="1" name="cerials">
      <description>
        cerials
      </description>
      <DPM const="1" max="2.29587" min="2.29587">
        2.295868
      </DPM>
      <RPM const="1" max="0.971577" min="0.971577">
        0.9715765671
      </RPM>
      <HUM const="1" max="0.0284234" min="0.0284234">
        0.0284234329
      </HUM>
      
    </PlantFraction>
    <PlantFraction id="2" name="green">
      <description>
        green
      </description>
      <DPM const="1" max="0" min="0">
        0
      </DPM>
      <RPM const="1" max="0.983167" min="0.983167">
        0.9831671105
      </RPM>
      <HUM const="1" max="0.0168329" min="0.0168329">
        0.0168328895000001
      </HUM>
      
    </PlantFraction>
    <PlantFraction id="3" name="root">
      <description>
        root
      </description>
      <DPM const="1" max="0" min="0">
        0
      </DPM>
      <RPM const="1" max="0.88565" min="0.88565">
        0.8856502603
      </RPM>
      <HUM const="1" max="0.11435" min="0.11435">
        0.1143497397
      </HUM>
      
    </PlantFraction>
    
  </PlantFractions>
  <FertilizerFractions>
    <FertilizerFraction id="0" name="default">
      <description>
        The default ratio parameter for farmyard manure
      </description>
      <DPM const="1" max="0.49" min="0.49">
        0.49
      </DPM>
      <RPM const="1" max="0.49" min="0.49">
        0.49
      </RPM>
      <HUM const="1" max="0.02" min="0.02">
        0.02
      </HUM>
      
    </FertilizerFraction>
    <FertilizerFraction id="1" name="1">
      <description>
        1
      </description>
      <DPM const="1" max="0" min="0">
        0
      </DPM>
      <RPM const="1" max="0.581788" min="0.581788">
        0.5817882478
      </RPM>
      <HUM const="1" max="0.418212" min="0.418212">
        0.4182117522
      </HUM>
      
    </FertilizerFraction>
    <FertilizerFraction id="2" name="2">
      <description>
        2
      </description>
      <DPM const="1" max="0" min="0">
        0
      </DPM>
      <RPM const="1" max="0.748873" min="0.748873">
        0.7488733795
      </RPM>
      <HUM const="1" max="0.251127" min="0.251127">
        0.2511266205
      </HUM>
      
    </FertilizerFraction>
    <FertilizerFraction id="3" name="3">
      <description>
        3
      </description>
      <DPM const="1" max="0" min="0">
        0
      </DPM>
      <RPM const="1" max="0" min="0">
        0
      </RPM>
      <HUM const="1" max="0.264373" min="0.264373">
        0.264372672
      </HUM>
      
    </FertilizerFraction>
    <FertilizerFraction id="4" name="4">
      <description>
        4
      </description>
      <DPM const="1" max="0.735627" min="0.735627">
        0.735627328
      </DPM>
      <RPM const="1" max="0.81802" min="0.81802">
        0.8180201517
      </RPM>
      <HUM const="1" max="0.18198" min="0.18198">
        0.1819798483
      </HUM>
      
    </FertilizerFraction>
    <FertilizerFraction id="5" name="5">
      <description>
        5
      </description>
      <DPM const="1" max="0" min="0">
        0
      </DPM>
      <RPM const="1" max="0.373176" min="0.373176">
        0.3731757889
      </RPM>
      <HUM const="1" max="0.626824" min="0.626824">
        0.6268242111
      </HUM>
      
    </FertilizerFraction>
    <FertilizerFraction id="6" name="6">
      <description>
        6
      </description>
      <DPM const="1" max="0" min="0">
        0
      </DPM>
      <RPM const="1" max="0.145239" min="0.145239">
        0.145239342
      </RPM>
      <HUM const="1" max="0.854761" min="0.854761">
        0.854760658
      </HUM>
      
    </FertilizerFraction>
    <FertilizerFraction id="7" name="7">
      <description>
        7
      </description>
      <DPM const="1" max="0" min="0">
        0
      </DPM>
      <RPM const="1" max="0.683749" min="0.683749">
        0.6837492303
      </RPM>
      <HUM const="1" max="0.316251" min="0.316251">
        0.3162507697
      </HUM>
      
    </FertilizerFraction>
    <FertilizerFraction id="8" name="8">
      <description>
        8
      </description>
      <DPM const="1" max="0" min="0">
        0
      </DPM>
      <RPM const="1" max="0.932854" min="0.932854">
        0.9328535278
      </RPM>
      <HUM const="1" max="0.0671465" min="0.0671465">
        0.0671464722
      </HUM>
      
    </FertilizerFraction>
    <FertilizerFraction id="9" name="9">
      <description>
        9
      </description>
      <DPM const="1" max="0" min="0">
        0
      </DPM>
      <RPM const="1" max="0.567919" min="0.567919">
        0.5679188596
      </RPM>
      <HUM const="1" max="0.432081" min="0.432081">
        0.4320811404
      </HUM>
      
    </FertilizerFraction>
    <FertilizerFraction id="10" name="10">
      <description>
        10
      </description>
      <DPM const="1" max="0" min="0">
        0
      </DPM>
      <RPM const="1" max="0.605189" min="0.605189">
        0.6051887504
      </RPM>
      <HUM const="1" max="0.394811" min="0.394811">
        0.3948112496
      </HUM>
      
    </FertilizerFraction>
    <FertilizerFraction id="11" name="11">
      <description>
        11
      </description>
      <DPM const="1" max="0" min="0">
        0
      </DPM>
      <RPM const="1" max="0.795199" min="0.795199">
        0.7951989838
      </RPM>
      <HUM const="1" max="0.204801" min="0.204801">
        0.2048010162
      </HUM>
      
    </FertilizerFraction>
    <FertilizerFraction id="12" name="12">
      <description>
        12
      </description>
      <DPM const="1" max="0" min="0">
        0
      </DPM>
      <RPM const="1" max="0.873969" min="0.873969">
        0.873969256
      </RPM>
      <HUM const="1" max="0.126031" min="0.126031">
        0.126030744
      </HUM>
      
    </FertilizerFraction>
    <FertilizerFraction id="13" name="13">
      <description>
        13
      </description>
      <DPM const="1" max="0" min="0">
        0
      </DPM>
      <RPM const="1" max="0.829838" min="0.829838">
        0.8298378097
      </RPM>
      <HUM const="1" max="0.170162" min="0.170162">
        0.1701621903
      </HUM>
      
    </FertilizerFraction>
    <FertilizerFraction id="14" name="14">
      <description>
        14
      </description>
      <DPM const="1" max="0" min="0">
        0
      </DPM>
      <RPM const="1" max="0.357374" min="0.357374">
        0.3573740019
      </RPM>
      <HUM const="1" max="0.642626" min="0.642626">
        0.6426259981
      </HUM>
      
    </FertilizerFraction>
    <FertilizerFraction id="15" name="15">
      <description>
        15
      </description>
      <DPM const="1" max="0" min="0">
        0
      </DPM>
      <RPM const="1" max="0.613875" min="0.613875">
        0.6138749215
      </RPM>
      <HUM const="1" max="0.386125" min="0.386125">
        0.3861250785
      </HUM>
      
    </FertilizerFraction>
    <FertilizerFraction id="16" name="16">
      <description>
        16
      </description>
      <DPM const="1" max="0" min="0">
        0
      </DPM>
      <RPM const="1" max="0.622401" min="0.622401">
        0.6224013425
      </RPM>
      <HUM const="1" max="0.377599" min="0.377599">
        0.3775986575
      </HUM>
      
    </FertilizerFraction>
    <FertilizerFraction id="17" name="17">
      <description>
        17
      </description>
      <DPM const="1" max="0" min="0">
        0
      </DPM>
      <RPM const="1" max="0.2259" min="0.2259">
        0.2258996696
      </RPM>
      <HUM const="1" max="0.7741" min="0.7741">
        0.7741003304
      </HUM>
      
    </FertilizerFraction>
    <FertilizerFraction id="18" name="18">
      <description>
        18
      </description>
      <DPM const="1" max="0" min="0">
        0
      </DPM>
      <RPM const="1" max="0.379685" min="0.379685">
        0.3796851243
      </RPM>
      <HUM const="1" max="0.620315" min="0.620315">
        0.6203148757
      </HUM>
      
    </FertilizerFraction>
    <FertilizerFraction id="19" name="19">
      <description>
        19
      </description>
      <DPM const="1" max="0" min="0">
        0
      </DPM>
      <RPM const="1" max="0.450247" min="0.450247">
        0.450246551
      </RPM>
      <HUM const="1" max="0.549753" min="0.549753">
        0.549753449
      </HUM>
      
    </FertilizerFraction>
    <FertilizerFraction id="20" name="20">
      <description>
        20
      </description>
      <DPM const="1" max="0" min="0">
        0
      </DPM>
      <RPM const="1" max="0.60157" min="0.60157">
        0.6015703144
      </RPM>
      <HUM const="1" max="0.39843" min="0.39843">
        0.3984296856
      </HUM>
      
    </FertilizerFraction>
    <FertilizerFraction id="21" name="21">
      <description>
        21
      </description>
      <DPM const="1" max="0" min="0">
        0
      </DPM>
      <RPM const="1" max="0.290731" min="0.290731">
        0.2907312644
      </RPM>
      <HUM const="1" max="0.709269" min="0.709269">
        0.7092687356
      </HUM>
      
    </FertilizerFraction>
    <FertilizerFraction id="22" name="22">
      <description>
        22
      </description>
      <DPM const="1" max="0" min="0">
        0
      </DPM>
      <RPM const="1" max="0" min="0">
        0
      </RPM>
      <HUM const="1" max="0.726437" min="0.726437">
        0.726437184
      </HUM>
      
    </FertilizerFraction>
    <FertilizerFraction id="23" name="23">
      <description>
        23
      </description>
      <DPM const="1" max="0.273563" min="0.273563">
        0.273562816
      </DPM>
      <RPM const="1" max="0.833094" min="0.833094">
        0.8330944021
      </RPM>
      <HUM const="1" max="0.166906" min="0.166906">
        0.1669055979
      </HUM>
      
    </FertilizerFraction>
    <FertilizerFraction id="24" name="24">
      <description>
        24
      </description>
      <DPM const="1" max="0" min="0">
        0
      </DPM>
      <RPM const="1" max="0.538683" min="0.538683">
        0.5386826666
      </RPM>
      <HUM const="1" max="0.461317" min="0.461317">
        0.4613173334
      </HUM>
      
    </FertilizerFraction>
    
  </FertilizerFractions>
  
</RothC>
