<RothC xmlns="http://tag2e.googlecode.com/files/RothC" xmlns:xsi="http://www.w3.org/2001/XMLSchema-instance" xsi:schemaLocation="http://tag2e.googlecode.com/files/RothC http://tag2e.googlecode.com/files/RothC.xsd">
  <a>
    <a1 const="1" max="2.00032" min="2.00032">
      2.000319
    </a1>
    <a2 const="1" max="31.8033" min="31.8033">
      31.803337
    </a2>
    <a3 const="1" max="18.3" min="18.3">
      18.3
    </a3>
    
  </a>
  <b>
    <b1 const="1" max="0.267351" min="0.267351">
      0.267351
    </b1>
    <b2 const="1" max="1" min="1">
      1
    </b2>
    <b3 const="1" max="0" min="0">
      0.0
    </b3>
    
  </b>
  <c>
    <c1 const="1" max="0.6" min="0.6">
      0.6
    </c1>
    <c2 const="1" max="1" min="1">
      1
    </c2>
    
  </c>
  <k>
    <DPM const="1" max="10.2" min="10.2">
      10.2
    </DPM>
    <RPM const="1" max="0.3" min="0.3">
      0.3
    </RPM>
    <BIO const="1" max="0.66" min="0.66">
      0.66
    </BIO>
    <HUM const="1" max="0.02" min="0.02">
      0.02
    </HUM>
    
  </k>
  <x>
    <x1 const="1" max="0.46" min="0.46">
      0.46
    </x1>
    <x2 const="1" max="1.85" min="1.85">
      1.85
    </x2>
    <x3 const="1" max="109.869" min="109.869">
      109.869439
    </x3>
    <x4 const="1" max="-0.0786" min="-0.0786">
      -0.0786
    </x4>
    
  </x>
  <PlantFractions>
    <PlantFraction id="0" name="default">
      <description>
        The default ratio parameter for agricultural crops and grassland
      </description>
      <DPM const="1" max="0.59" min="0.59">
        0.59
      </DPM>
      <RPM const="1" max="0.41" min="0.41">
        0.41
      </RPM>
      <HUM const="1" max="0" min="0">
        0
      </HUM>
      
    </PlantFraction>
    <PlantFraction id="1" name="cerials">
      <description>
        cerials
      </description>
      <DPM const="1" max="2.36011" min="2.36011">
        2.360111
      </DPM>
      <RPM const="1" max="0.979171" min="0.979171">
        0.9791714333
      </RPM>
      <HUM const="1" max="0.0208286" min="0.0208286">
        0.0208285667000001
      </HUM>
      
    </PlantFraction>
    <PlantFraction id="2" name="green">
      <description>
        green
      </description>
      <DPM const="1" max="0" min="0">
        0
      </DPM>
      <RPM const="1" max="0.984435" min="0.984435">
        0.9844354878
      </RPM>
      <HUM const="1" max="0.0155645" min="0.0155645">
        0.0155645122000001
      </HUM>
      
    </PlantFraction>
    <PlantFraction id="3" name="root">
      <description>
        root
      </description>
      <DPM const="1" max="0" min="0">
        0
      </DPM>
      <RPM const="1" max="0.890212" min="0.890212">
        0.8902117993
      </RPM>
      <HUM const="1" max="0.109788" min="0.109788">
        0.1097882007
      </HUM>
      
    </PlantFraction>
    
  </PlantFractions>
  <FertilizerFractions>
    <FertilizerFraction id="0" name="default">
      <description>
        The default ratio parameter for farmyard manure
      </description>
      <DPM const="1" max="0.49" min="0.49">
        0.49
      </DPM>
      <RPM const="1" max="0.49" min="0.49">
        0.49
      </RPM>
      <HUM const="1" max="0.02" min="0.02">
        0.02
      </HUM>
      
    </FertilizerFraction>
    <FertilizerFraction id="1" name="1">
      <description>
        1
      </description>
      <DPM const="1" max="0" min="0">
        0
      </DPM>
      <RPM const="1" max="0.567534" min="0.567534">
        0.5675339196
      </RPM>
      <HUM const="1" max="0.432466" min="0.432466">
        0.4324660804
      </HUM>
      
    </FertilizerFraction>
    <FertilizerFraction id="2" name="2">
      <description>
        2
      </description>
      <DPM const="1" max="0" min="0">
        0
      </DPM>
      <RPM const="1" max="0.746762" min="0.746762">
        0.7467619836
      </RPM>
      <HUM const="1" max="0.253238" min="0.253238">
        0.2532380164
      </HUM>
      
    </FertilizerFraction>
    <FertilizerFraction id="3" name="3">
      <description>
        3
      </description>
      <DPM const="1" max="0" min="0">
        0
      </DPM>
      <RPM const="1" max="0" min="0">
        0
      </RPM>
      <HUM const="1" max="0.190167" min="0.190167">
        0.190167072
      </HUM>
      
    </FertilizerFraction>
    <FertilizerFraction id="4" name="4">
      <description>
        4
      </description>
      <DPM const="1" max="0.809833" min="0.809833">
        0.809832928
      </DPM>
      <RPM const="1" max="0.766644" min="0.766644">
        0.7666441346
      </RPM>
      <HUM const="1" max="0.233356" min="0.233356">
        0.2333558654
      </HUM>
      
    </FertilizerFraction>
    <FertilizerFraction id="5" name="5">
      <description>
        5
      </description>
      <DPM const="1" max="0" min="0">
        0
      </DPM>
      <RPM const="1" max="0.334239" min="0.334239">
        0.3342391079
      </RPM>
      <HUM const="1" max="0.665761" min="0.665761">
        0.6657608921
      </HUM>
      
    </FertilizerFraction>
    <FertilizerFraction id="6" name="6">
      <description>
        6
      </description>
      <DPM const="1" max="0" min="0">
        0
      </DPM>
      <RPM const="1" max="0.103437" min="0.103437">
        0.1034367827
      </RPM>
      <HUM const="1" max="0.896563" min="0.896563">
        0.8965632173
      </HUM>
      
    </FertilizerFraction>
    <FertilizerFraction id="7" name="7">
      <description>
        7
      </description>
      <DPM const="1" max="0" min="0">
        0
      </DPM>
      <RPM const="1" max="0.706601" min="0.706601">
        0.7066011934
      </RPM>
      <HUM const="1" max="0.293399" min="0.293399">
        0.2933988066
      </HUM>
      
    </FertilizerFraction>
    <FertilizerFraction id="8" name="8">
      <description>
        8
      </description>
      <DPM const="1" max="0" min="0">
        0
      </DPM>
      <RPM const="1" max="0.975091" min="0.975091">
        0.9750910693
      </RPM>
      <HUM const="1" max="0.0249089" min="0.0249089">
        0.0249089307000001
      </HUM>
      
    </FertilizerFraction>
    <FertilizerFraction id="9" name="9">
      <description>
        9
      </description>
      <DPM const="1" max="0" min="0">
        0
      </DPM>
      <RPM const="1" max="0.539668" min="0.539668">
        0.539668113
      </RPM>
      <HUM const="1" max="0.460332" min="0.460332">
        0.460331887
      </HUM>
      
    </FertilizerFraction>
    <FertilizerFraction id="10" name="10">
      <description>
        10
      </description>
      <DPM const="1" max="0" min="0">
        0
      </DPM>
      <RPM const="1" max="0.578226" min="0.578226">
        0.5782256281
      </RPM>
      <HUM const="1" max="0.421774" min="0.421774">
        0.4217743719
      </HUM>
      
    </FertilizerFraction>
    <FertilizerFraction id="11" name="11">
      <description>
        11
      </description>
      <DPM const="1" max="0" min="0">
        0
      </DPM>
      <RPM const="1" max="0.738555" min="0.738555">
        0.7385550628
      </RPM>
      <HUM const="1" max="0.261445" min="0.261445">
        0.2614449372
      </HUM>
      
    </FertilizerFraction>
    <FertilizerFraction id="12" name="12">
      <description>
        12
      </description>
      <DPM const="1" max="0" min="0">
        0
      </DPM>
      <RPM const="1" max="0.858751" min="0.858751">
        0.8587506531
      </RPM>
      <HUM const="1" max="0.141249" min="0.141249">
        0.1412493469
      </HUM>
      
    </FertilizerFraction>
    <FertilizerFraction id="13" name="13">
      <description>
        13
      </description>
      <DPM const="1" max="0" min="0">
        0
      </DPM>
      <RPM const="1" max="0.858602" min="0.858602">
        0.8586024512
      </RPM>
      <HUM const="1" max="0.141398" min="0.141398">
        0.1413975488
      </HUM>
      
    </FertilizerFraction>
    <FertilizerFraction id="14" name="14">
      <description>
        14
      </description>
      <DPM const="1" max="0" min="0">
        0
      </DPM>
      <RPM const="1" max="0.484375" min="0.484375">
        0.4843753314
      </RPM>
      <HUM const="1" max="0.515625" min="0.515625">
        0.5156246686
      </HUM>
      
    </FertilizerFraction>
    <FertilizerFraction id="15" name="15">
      <description>
        15
      </description>
      <DPM const="1" max="0" min="0">
        0
      </DPM>
      <RPM const="1" max="0.510511" min="0.510511">
        0.5105108327
      </RPM>
      <HUM const="1" max="0.489489" min="0.489489">
        0.4894891673
      </HUM>
      
    </FertilizerFraction>
    <FertilizerFraction id="16" name="16">
      <description>
        16
      </description>
      <DPM const="1" max="0" min="0">
        0
      </DPM>
      <RPM const="1" max="0.619399" min="0.619399">
        0.6193988105
      </RPM>
      <HUM const="1" max="0.380601" min="0.380601">
        0.3806011895
      </HUM>
      
    </FertilizerFraction>
    <FertilizerFraction id="17" name="17">
      <description>
        17
      </description>
      <DPM const="1" max="0" min="0">
        0
      </DPM>
      <RPM const="1" max="0.287604" min="0.287604">
        0.2876036269
      </RPM>
      <HUM const="1" max="0.712396" min="0.712396">
        0.7123963731
      </HUM>
      
    </FertilizerFraction>
    <FertilizerFraction id="18" name="18">
      <description>
        18
      </description>
      <DPM const="1" max="0" min="0">
        0
      </DPM>
      <RPM const="1" max="0.363498" min="0.363498">
        0.3634983973
      </RPM>
      <HUM const="1" max="0.636502" min="0.636502">
        0.6365016027
      </HUM>
      
    </FertilizerFraction>
    <FertilizerFraction id="19" name="19">
      <description>
        19
      </description>
      <DPM const="1" max="0" min="0">
        0
      </DPM>
      <RPM const="1" max="0.531484" min="0.531484">
        0.5314842886
      </RPM>
      <HUM const="1" max="0.468516" min="0.468516">
        0.4685157114
      </HUM>
      
    </FertilizerFraction>
    <FertilizerFraction id="20" name="20">
      <description>
        20
      </description>
      <DPM const="1" max="0" min="0">
        0
      </DPM>
      <RPM const="1" max="0.704076" min="0.704076">
        0.704075987
      </RPM>
      <HUM const="1" max="0.295924" min="0.295924">
        0.295924013
      </HUM>
      
    </FertilizerFraction>
    <FertilizerFraction id="21" name="21">
      <description>
        21
      </description>
      <DPM const="1" max="0" min="0">
        0
      </DPM>
      <RPM const="1" max="0.338029" min="0.338029">
        0.3380288422
      </RPM>
      <HUM const="1" max="0.661971" min="0.661971">
        0.6619711578
      </HUM>
      
    </FertilizerFraction>
    <FertilizerFraction id="22" name="22">
      <description>
        22
      </description>
      <DPM const="1" max="0" min="0">
        0
      </DPM>
      <RPM const="1" max="0" min="0">
        0
      </RPM>
      <HUM const="1" max="0.815141" min="0.815141">
        0.815140512
      </HUM>
      
    </FertilizerFraction>
    <FertilizerFraction id="23" name="23">
      <description>
        23
      </description>
      <DPM const="1" max="0.184859" min="0.184859">
        0.184859488
      </DPM>
      <RPM const="1" max="0.782554" min="0.782554">
        0.7825537048
      </RPM>
      <HUM const="1" max="0.217446" min="0.217446">
        0.2174462952
      </HUM>
      
    </FertilizerFraction>
    <FertilizerFraction id="24" name="24">
      <description>
        24
      </description>
      <DPM const="1" max="0" min="0">
        0
      </DPM>
      <RPM const="1" max="0.469434" min="0.469434">
        0.4694338853
      </RPM>
      <HUM const="1" max="0.530566" min="0.530566">
        0.5305661147
      </HUM>
      
    </FertilizerFraction>
    
  </FertilizerFractions>
  
</RothC>
